{
  "id": "spamhat",
  "name": "SpamHAT",
  "type": "import",
  "category": "Honeypot",
  "description": "Spam Honeypot Tool. Tool: https://github.com/miguelraulb/spamhat. [SCAFFOLD generated from XORCISM.TOOL #585 by tool_to_connector.py — implement run() in run.py to map SpamHAT output to the XORCISM findings model {assets, services, cpes, vulns}.]",
  "intrusive": false,
  "permission": "connector:spamhat",
  "run": "run.py",
  "mapping": "spamhat",
  "parameters": [
    {
      "name": "target",
      "type": "string",
      "required": false,
      "help": "Host, URL or path the tool acts on. When implementing, consider type 'target' or 'url' so the runner enforces the engagement scope."
    },
    {
      "name": "file",
      "type": "file",
      "required": false,
      "help": "Offline mode: a saved SpamHAT output file to parse instead of running it live."
    }
  ]
}
