{
  "id": "ghiro",
  "name": "Ghiro",
  "type": "import",
  "category": "OSINT",
  "description": "Automated digital image forensics Tool: https://www.getghiro.org. [SCAFFOLD generated from XORCISM.TOOL #1091 by tool_to_connector.py — implement run() in run.py to map Ghiro output to the XORCISM findings model {assets, services, cpes, vulns}.]",
  "intrusive": false,
  "permission": "connector:ghiro",
  "run": "run.py",
  "mapping": "ghiro",
  "parameters": [
    {
      "name": "target",
      "type": "string",
      "required": false,
      "help": "Host, URL or path the tool acts on. When implementing, consider type 'target' or 'url' so the runner enforces the engagement scope."
    },
    {
      "name": "file",
      "type": "file",
      "required": false,
      "help": "Offline mode: a saved Ghiro output file to parse instead of running it live."
    }
  ]
}
